diamond_miner/__init__.py
diamond_miner/defaults.py
diamond_miner/format.py
diamond_miner/generators/__init__.py
diamond_miner/generators/database.py
diamond_miner/generators/parallel.py
diamond_miner/generators/standalone.py
diamond_miner/grid.py
diamond_miner/insert.py
diamond_miner/logger.py
diamond_miner/mappers.py
diamond_miner/mda.py
diamond_miner/py.typed
diamond_miner/queries/__init__.py
diamond_miner/queries/count.py
diamond_miner/queries/count_rows.py
diamond_miner/queries/create_links_table.py
diamond_miner/queries/create_prefixes_table.py
diamond_miner/queries/create_probes_table.py
diamond_miner/queries/create_results_table.py
diamond_miner/queries/create_tables.py
diamond_miner/queries/delete_probes.py
diamond_miner/queries/drop_tables.py
diamond_miner/queries/fragments.py
diamond_miner/queries/get_invalid_prefixes.py
diamond_miner/queries/get_links.py
diamond_miner/queries/get_links_from_results.py
diamond_miner/queries/get_mda_probes.py
diamond_miner/queries/get_nodes.py
diamond_miner/queries/get_prefixes.py
diamond_miner/queries/get_probes.py
diamond_miner/queries/get_results.py
diamond_miner/queries/get_sliding_prefixes.py
diamond_miner/queries/insert_links.py
diamond_miner/queries/insert_mda_probes.py
diamond_miner/queries/insert_prefixes.py
diamond_miner/queries/insert_results.py
diamond_miner/queries/query.py
diamond_miner/subsets.py
diamond_miner/test.py
diamond_miner/typing.py
diamond_miner/utilities.py
diamond_miner_elena-1.1.2.dist-info/METADATA
diamond_miner_elena-1.1.2.dist-info/WHEEL
diamond_miner_elena-1.1.2.dist-info/licenses/LICENSE
diamond_miner_elena-1.1.2.dist-info/RECORD
