Metadata-Version: 2.4
Name: diamond-miner-elena
Version: 1.1.2
Summary: High-speed, Internet-scale, load-balanced paths discovery.
License: MIT
License-File: LICENSE
Author: Kevin Vermeulen
Author-email: kevin.vermeulen@columbia.edu
Requires-Python: >=3.10,<4.0
Classifier: Development Status :: 5 - Production/Stable
Classifier: Intended Audience :: Science/Research
Classifier: License :: OSI Approved :: MIT License
Classifier: Operating System :: MacOS :: MacOS X
Classifier: Operating System :: POSIX :: Linux
Classifier: Programming Language :: Python :: 3
Classifier: Programming Language :: Python :: 3.10
Classifier: Programming Language :: Python :: 3.11
Classifier: Programming Language :: Python :: 3.12
Classifier: Programming Language :: Python :: 3.13
Classifier: Programming Language :: Python :: 3.14
Classifier: Topic :: Internet
Classifier: Typing :: Typed
Requires-Dist: pych-client (>=0.4.1,<0.5.0)
Requires-Dist: pygfc (>=1.0.5,<2.0.0)
Requires-Dist: tqdm (>=4.66.1,<5.0.0)
Requires-Dist: zstandard (>=0.21.0,<0.22.0)
Project-URL: Homepage, https://github.com/dioptra-io/diamond-miner
